{
  "rows": 545,
  "generated_at_utc": "20260405-225349Z",
  "leaderboard_path": "D:\\code\\agentic-development\\reinforcement-learning-stocks\\data\\experiment_snapshots\\experiment_leaderboard_20260405-225349Z_nvda-rx-v1-realism-s10-l10.csv",
  "reward_leaderboard_path": "D:\\code\\agentic-development\\reinforcement-learning-stocks\\data\\experiment_snapshots\\experiment_reward_leaderboard_20260405-225349Z_nvda-rx-v1-realism-s10-l10.csv",
  "top3": [
    {
      "ticker": "NVDA",
      "seed": 42,
      "timesteps": 12000,
      "learning_rate": 0.0001,
      "gamma": 0.99,
      "ent_coef": 0.05,
      "include_news": 1,
      "use_stationary_features": 1.0,
      "threshold": 0.002,
      "horizon": 1,
      "transaction_cost_rate": 0.001,
      "trade_penalty": 0.05,
      "execution_mode": "next_bar",
      "spread_bps": 0.0,
      "slippage_bps": 0.0,
      "reward_mode": "legacy",
      "rolling_reward_window": "100",
      "reward_epsilon": 1e-06,
      "reward_return_scale": 1.0,
      "reward_direction_scale": 0.45,
      "reward_hold_penalty_scale": 0.1,
      "reward_drawdown_penalty_scale": 0.1,
      "reward_action_bonus_scale": 0.01,
      "reward_clip": 1.0,
      "reward_ignore_transaction_cost": 1,
      "val_overall_accuracy": 0.064516129032258,
      "val_actionable_accuracy": 1.0,
      "val_actionable_support": 2.0,
      "val_trade_count": 2.0,
      "val_trade_rate": 0.0064516129032258,
      "val_trade_win_rate": 1.0,
      "val_cumulative_signal_return": 0.053999729240584,
      "test_overall_accuracy": 0.0739549839228295,
      "test_actionable_accuracy": 0.5,
      "test_actionable_support": 2.0,
      "test_trade_count": 2.0,
      "test_trade_rate": 0.0064308681672025,
      "test_trade_win_rate": 0.5,
      "test_cumulative_signal_return": -0.0002965079896425,
      "val_alpha_vs_qqq": -0.3791652614035037,
      "test_alpha_vs_qqq": -0.1575918231647769,
      "ranking_score": 0.8107999458481169,
      "run_duration_seconds": 37.16087341308594,
      "val_reward_total_mean": -0.001959010378121,
      "val_reward_total_sum": -0.6072932172175343,
      "val_reward_portfolio_return_mean": 4.133515187000444e-05,
      "val_reward_direction_mean": 4.5940413652829584e-05,
      "val_reward_hold_penalty_mean": -0.0023270807025215,
      "val_reward_action_bonus_mean": 0.000516129032258,
      "val_reward_drawdown_penalty_mean": -0.0001707357742841,
      "val_reward_drawdown_mean": 0.0017073577428412,
      "test_reward_total_mean": -0.0035970014984055,
      "test_reward_total_sum": -1.1186674660041156,
      "test_reward_portfolio_return_mean": -9.524035159684008e-05,
      "test_reward_direction_mean": -1.5796040138972037e-05,
      "test_reward_hold_penalty_mean": -0.0020687500360974,
      "test_reward_action_bonus_mean": 0.0005466237942122,
      "test_reward_drawdown_penalty_mean": -0.0019285577381807,
      "test_reward_drawdown_mean": 0.019285577381807,
      "val_cumulative_return": 0.0127760698509222,
      "val_sharpe_ratio": 0.748845649232497,
      "val_sortino_ratio": 0.6194165753585025,
      "val_max_drawdown": -0.0068977475060345,
      "test_cumulative_return": -0.0295499372634878,
      "test_sharpe_ratio": -0.9741417405819712,
      "test_sortino_ratio": -0.6362965947212944,
      "test_max_drawdown": -0.0333635466417694,
      "val_benchmark_cumulative_return": 0.391941331254426,
      "val_benchmark_sharpe_ratio": 1.625408332669604,
      "val_benchmark_sortino_ratio": 2.208505179591514,
      "val_benchmark_max_drawdown": -0.1355773890565936,
      "test_benchmark_cumulative_return": 0.128041885901289,
      "test_benchmark_sharpe_ratio": 0.5431946432399444,
      "test_benchmark_sortino_ratio": 0.7349245650013833,
      "test_benchmark_max_drawdown": -0.228833069215711,
      "model_path": "D:\\code\\agentic-development\\reinforcement-learning-stocks\\data\\experiment_snapshots\\model_20260405-214128Z_nvda-exp4-legacy-swap_seed42.zip",
      "test_return_mean_by_config": -0.0092801411565655,
      "test_return_std_by_config": 0.2137077190403933,
      "config_seed_count": 5.0,
      "test_return_cv_by_config": 23.02849875178866,
      "high_return_cv_risk": 1.0,
      "robustness_score": 0.7200407635316391,
      "run_label": "nvda-exp4-legacy-swap",
      "reward_turnover_penalty_scale": 0.01,
      "val_reward_turnover_penalty_mean": 0.0,
      "test_reward_turnover_penalty_mean": 0.0
    },
    {
      "ticker": "NVDA",
      "seed": 7,
      "timesteps": 12000,
      "learning_rate": 0.0001,
      "gamma": 0.99,
      "ent_coef": 0.05,
      "include_news": 1,
      "use_stationary_features": 1.0,
      "threshold": 0.003,
      "horizon": 1,
      "transaction_cost_rate": 0.001,
      "trade_penalty": 0.05,
      "execution_mode": "next_bar",
      "spread_bps": 0.0,
      "slippage_bps": 0.0,
      "reward_mode": "sharpe",
      "rolling_reward_window": "100",
      "reward_epsilon": 1e-06,
      "reward_return_scale": 1.0,
      "reward_direction_scale": 0.45,
      "reward_hold_penalty_scale": 0.1,
      "reward_drawdown_penalty_scale": 0.1,
      "reward_action_bonus_scale": 0.0,
      "reward_clip": 1.0,
      "reward_ignore_transaction_cost": 1,
      "val_overall_accuracy": 0.1032258064516129,
      "val_actionable_accuracy": 1.0,
      "val_actionable_support": 2.0,
      "val_trade_count": 2.0,
      "val_trade_rate": 0.0064516129032258,
      "val_trade_win_rate": 1.0,
      "val_cumulative_signal_return": 0.0270778967553904,
      "test_overall_accuracy": 0.1061093247588424,
      "test_actionable_accuracy": 0.5,
      "test_actionable_support": 2.0,
      "test_trade_count": 3.0,
      "test_trade_rate": 0.0096463022508038,
      "test_trade_win_rate": 0.3333333333333333,
      "test_cumulative_signal_return": 0.0071038818823139,
      "val_alpha_vs_qqq": -0.3719516402410894,
      "test_alpha_vs_qqq": -0.1277725482624339,
      "ranking_score": 0.8054155793510781,
      "run_duration_seconds": 37.18555879592896,
      "val_reward_total_mean": 0.1197916906499601,
      "val_reward_total_sum": 37.13542410148765,
      "val_reward_portfolio_return_mean": 6.400185978737991e-05,
      "val_reward_direction_mean": 7.825489906980104e-05,
      "val_reward_hold_penalty_mean": -0.0023356642016569,
      "val_reward_action_bonus_mean": 0.0,
      "val_reward_drawdown_penalty_mean": -5.214573455511917e-05,
      "val_reward_drawdown_mean": 0.0005214573455511,
      "test_reward_total_mean": 0.0134781127928648,
      "test_reward_total_sum": 4.191693078580957,
      "test_reward_portfolio_return_mean": 8.786694673343499e-07,
      "test_reward_direction_mean": 2.84927988772139e-06,
      "test_reward_hold_penalty_mean": -0.0020703961854635,
      "test_reward_action_bonus_mean": 0.0,
      "test_reward_drawdown_penalty_mean": -0.0001066928883719,
      "test_reward_drawdown_mean": 0.0010669288837198,
      "val_cumulative_return": 0.0199896910133365,
      "val_sharpe_ratio": 1.8362817371550983,
      "val_sortino_ratio": 1.6659078987542706,
      "val_max_drawdown": -0.0066120488864273,
      "test_cumulative_return": 0.0002693376388551,
      "test_sharpe_ratio": 0.0873315603413295,
      "test_sortino_ratio": 0.0330757266608537,
      "test_max_drawdown": -0.0018615872213169,
      "val_benchmark_cumulative_return": 0.391941331254426,
      "val_benchmark_sharpe_ratio": 1.625408332669604,
      "val_benchmark_sortino_ratio": 2.208505179591514,
      "val_benchmark_max_drawdown": -0.1355773890565936,
      "test_benchmark_cumulative_return": 0.128041885901289,
      "test_benchmark_sharpe_ratio": 0.5431946432399444,
      "test_benchmark_sortino_ratio": 0.7349245650013833,
      "test_benchmark_max_drawdown": -0.228833069215711,
      "model_path": "D:\\code\\agentic-development\\reinforcement-learning-stocks\\data\\experiment_snapshots\\model_20260405-211426Z_nvda-exp2-action-turnover-threshold-0p003_seed7.zip",
      "test_return_mean_by_config": 0.1367628142394885,
      "test_return_std_by_config": 0.1871548473283542,
      "config_seed_count": 4.0,
      "test_return_cv_by_config": 1.3684629726953628,
      "high_return_cv_risk": 1.0,
      "robustness_score": 0.7539536947978811,
      "run_label": "nvda-exp2-action-turnover-threshold-0p003",
      "reward_turnover_penalty_scale": 0.0,
      "val_reward_turnover_penalty_mean": 0.0,
      "test_reward_turnover_penalty_mean": 0.0
    },
    {
      "ticker": "NVDA",
      "seed": 7,
      "timesteps": 12000,
      "learning_rate": 0.0001,
      "gamma": 0.99,
      "ent_coef": 0.05,
      "include_news": 1,
      "use_stationary_features": 1.0,
      "threshold": 0.002,
      "horizon": 1,
      "transaction_cost_rate": 0.001,
      "trade_penalty": 0.05,
      "execution_mode": "next_bar",
      "spread_bps": 0.0,
      "slippage_bps": 0.0,
      "reward_mode": "sharpe",
      "rolling_reward_window": "100",
      "reward_epsilon": 1e-06,
      "reward_return_scale": 1.0,
      "reward_direction_scale": 0.45,
      "reward_hold_penalty_scale": 0.1,
      "reward_drawdown_penalty_scale": 0.1,
      "reward_action_bonus_scale": 0.0,
      "reward_clip": 1.0,
      "reward_ignore_transaction_cost": 1,
      "val_overall_accuracy": 0.064516129032258,
      "val_actionable_accuracy": 1.0,
      "val_actionable_support": 2.0,
      "val_trade_count": 2.0,
      "val_trade_rate": 0.0064516129032258,
      "val_trade_win_rate": 1.0,
      "val_cumulative_signal_return": 0.0270778967553904,
      "test_overall_accuracy": 0.0739549839228295,
      "test_actionable_accuracy": 0.3333333333333333,
      "test_actionable_support": 3.0,
      "test_trade_count": 3.0,
      "test_trade_rate": 0.0096463022508038,
      "test_trade_win_rate": 0.3333333333333333,
      "test_cumulative_signal_return": 0.0071038818823139,
      "val_alpha_vs_qqq": -0.3719516402410894,
      "test_alpha_vs_qqq": -0.1277725482624339,
      "ranking_score": 0.8054155793510781,
      "run_duration_seconds": 38.702329874038696,
      "val_reward_total_mean": 0.1197916906499601,
      "val_reward_total_sum": 37.13542410148765,
      "val_reward_portfolio_return_mean": 6.400185978737991e-05,
      "val_reward_direction_mean": 7.825489906980104e-05,
      "val_reward_hold_penalty_mean": -0.0023356642016569,
      "val_reward_action_bonus_mean": 0.0,
      "val_reward_drawdown_penalty_mean": -5.214573455511917e-05,
      "val_reward_drawdown_mean": 0.0005214573455511,
      "test_reward_total_mean": 0.0134781127928648,
      "test_reward_total_sum": 4.191693078580957,
      "test_reward_portfolio_return_mean": 8.786694673343499e-07,
      "test_reward_direction_mean": 2.84927988772139e-06,
      "test_reward_hold_penalty_mean": -0.0020703961854635,
      "test_reward_action_bonus_mean": 0.0,
      "test_reward_drawdown_penalty_mean": -0.0001066928883719,
      "test_reward_drawdown_mean": 0.0010669288837198,
      "val_cumulative_return": 0.0199896910133365,
      "val_sharpe_ratio": 1.8362817371550983,
      "val_sortino_ratio": 1.6659078987542706,
      "val_max_drawdown": -0.0066120488864273,
      "test_cumulative_return": 0.0002693376388551,
      "test_sharpe_ratio": 0.0873315603413295,
      "test_sortino_ratio": 0.0330757266608537,
      "test_max_drawdown": -0.0018615872213169,
      "val_benchmark_cumulative_return": 0.391941331254426,
      "val_benchmark_sharpe_ratio": 1.625408332669604,
      "val_benchmark_sortino_ratio": 2.208505179591514,
      "val_benchmark_max_drawdown": -0.1355773890565936,
      "test_benchmark_cumulative_return": 0.128041885901289,
      "test_benchmark_sharpe_ratio": 0.5431946432399444,
      "test_benchmark_sortino_ratio": 0.7349245650013833,
      "test_benchmark_max_drawdown": -0.228833069215711,
      "model_path": "D:\\code\\agentic-development\\reinforcement-learning-stocks\\data\\experiment_snapshots\\model_20260405-210810Z_nvda-exp2-action-turnover-threshold-0p002_seed7.zip",
      "test_return_mean_by_config": 0.1367628142394885,
      "test_return_std_by_config": 0.1871548473283542,
      "config_seed_count": 4.0,
      "test_return_cv_by_config": 1.3684629726953628,
      "high_return_cv_risk": 1.0,
      "robustness_score": 0.7456203614645478,
      "run_label": "nvda-exp2-action-turnover-threshold-0p002",
      "reward_turnover_penalty_scale": 0.0,
      "val_reward_turnover_penalty_mean": 0.0,
      "test_reward_turnover_penalty_mean": 0.0
    }
  ]
}